[
  {
    "id": "4ef65d31-3203-4798-a559-78c99469e5a8",
    "module": "coding",
    "problem_id": "premium-24",
    "problem_title": "Flood Fill",
    "passed_tests": 3,
    "total_tests": 3,
    "percentage": 100.0,
    "timestamp": "2026-02-12T14:26:40.643224",
    "code_submitted": "def floodFill(image, sr, sc, newColor):\n    oldColor = image[sr][sc]\n    if oldColor == newColor:\n        return image\n\n    m, n = len(image), len(image[0])\n\n    def dfs(r, c):\n        if r < 0 or r >= m or c < 0 or c >= n:\n            return\n        if image[r][c] != oldColor:\n            return\n\n        image[r][c] = newColor\n\n        dfs(r+1, c)\n        dfs(r-1, c)\n        dfs(r, c+1)\n        dfs(r, c-1)\n\n    dfs(sr, sc)\n    return image\n",
    "user_id": "7f12936a-0622-4715-ad1a-e81e720ca132",
    "action": "run"
  },
  {
    "id": "e788a025-cfed-48d9-ab07-b6d6362646fa",
    "module": "coding",
    "problem_id": "premium-24",
    "problem_title": "Flood Fill",
    "passed_tests": 15,
    "total_tests": 15,
    "percentage": 100.0,
    "timestamp": "2026-02-12T14:26:45.321730",
    "code_submitted": "def floodFill(image, sr, sc, newColor):\n    oldColor = image[sr][sc]\n    if oldColor == newColor:\n        return image\n\n    m, n = len(image), len(image[0])\n\n    def dfs(r, c):\n        if r < 0 or r >= m or c < 0 or c >= n:\n            return\n        if image[r][c] != oldColor:\n            return\n\n        image[r][c] = newColor\n\n        dfs(r+1, c)\n        dfs(r-1, c)\n        dfs(r, c+1)\n        dfs(r, c-1)\n\n    dfs(sr, sc)\n    return image\n",
    "user_id": "7f12936a-0622-4715-ad1a-e81e720ca132",
    "action": "submit"
  },
  {
    "id": "9e81019f-919e-46aa-babf-02ced97d77dc",
    "module": "coding",
    "problem_id": "premium-24",
    "problem_title": "Flood Fill",
    "passed_tests": 3,
    "total_tests": 3,
    "percentage": 100.0,
    "timestamp": "2026-02-12T14:27:06.014320",
    "code_submitted": "class Solution {\n    public int[][] floodFill(int[][] image, int sr, int sc, int newColor) {\n        int oldColor = image[sr][sc];\n        if (oldColor == newColor) return image;\n\n        dfs(image, sr, sc, oldColor, newColor);\n        return image;\n    }\n\n    private void dfs(int[][] image, int r, int c, int oldColor, int newColor) {\n        if (r < 0 || r >= image.length || c < 0 || c >= image[0].length)\n            return;\n\n        if (image[r][c] != oldColor)\n            return;\n\n        image[r][c] = newColor;\n\n        dfs(image, r + 1, c, oldColor, newColor);\n        dfs(image, r - 1, c, oldColor, newColor);\n        dfs(image, r, c + 1, oldColor, newColor);\n        dfs(image, r, c - 1, oldColor, newColor);\n    }\n}\n",
    "user_id": "7f12936a-0622-4715-ad1a-e81e720ca132",
    "action": "run"
  },
  {
    "id": "89e5b1ca-d455-452a-9729-cfbb90d3d3ce",
    "module": "coding",
    "problem_id": "premium-24",
    "problem_title": "Flood Fill",
    "passed_tests": 15,
    "total_tests": 15,
    "percentage": 100.0,
    "timestamp": "2026-02-12T14:27:12.629491",
    "code_submitted": "class Solution {\n    public int[][] floodFill(int[][] image, int sr, int sc, int newColor) {\n        int oldColor = image[sr][sc];\n        if (oldColor == newColor) return image;\n\n        dfs(image, sr, sc, oldColor, newColor);\n        return image;\n    }\n\n    private void dfs(int[][] image, int r, int c, int oldColor, int newColor) {\n        if (r < 0 || r >= image.length || c < 0 || c >= image[0].length)\n            return;\n\n        if (image[r][c] != oldColor)\n            return;\n\n        image[r][c] = newColor;\n\n        dfs(image, r + 1, c, oldColor, newColor);\n        dfs(image, r - 1, c, oldColor, newColor);\n        dfs(image, r, c + 1, oldColor, newColor);\n        dfs(image, r, c - 1, oldColor, newColor);\n    }\n}\n",
    "user_id": "7f12936a-0622-4715-ad1a-e81e720ca132",
    "action": "submit"
  },
  {
    "id": "dfba52f5-fbe3-4556-afba-532bcdaf8375",
    "module": "coding",
    "problem_id": "premium-24",
    "problem_title": "Flood Fill",
    "passed_tests": 2,
    "total_tests": 3,
    "percentage": 66.66666666666666,
    "timestamp": "2026-02-12T14:27:33.420891",
    "code_submitted": "void dfs(int** image, int m, int n, int r, int c, int oldColor, int newColor) {\n    if (r < 0 || r >= m || c < 0 || c >= n)\n        return;\n    if (image[r][c] != oldColor)\n        return;\n\n    image[r][c] = newColor;\n\n    dfs(image, m, n, r+1, c, oldColor, newColor);\n    dfs(image, m, n, r-1, c, oldColor, newColor);\n    dfs(image, m, n, r, c+1, oldColor, newColor);\n    dfs(image, m, n, r, c-1, oldColor, newColor);\n}\n\nint** floodFill(int** image, int imageSize, int* imageColSize,\n                int sr, int sc, int newColor,\n                int* returnSize, int** returnColumnSizes) {\n\n    int oldColor = image[sr][sc];\n    if (oldColor == newColor)\n        return image;\n\n    dfs(image, imageSize, imageColSize[0], sr, sc, oldColor, newColor);\n\n    *returnSize = imageSize;\n    *returnColumnSizes = imageColSize;\n    return image;\n}\n\n",
    "user_id": "7f12936a-0622-4715-ad1a-e81e720ca132",
    "action": "run"
  },
  {
    "id": "17321d44-6d8f-40fb-b1f8-796c0cd23df3",
    "module": "coding",
    "problem_id": "premium-24",
    "problem_title": "Flood Fill",
    "passed_tests": 3,
    "total_tests": 3,
    "percentage": 100.0,
    "timestamp": "2026-02-12T14:27:57.797450",
    "code_submitted": "class Solution {\npublic:\n    void dfs(vector<vector<int>>& image, int r, int c, int oldColor, int newColor) {\n        if (r < 0 || r >= image.size() || c < 0 || c >= image[0].size())\n            return;\n        if (image[r][c] != oldColor)\n            return;\n\n        image[r][c] = newColor;\n\n        dfs(image, r+1, c, oldColor, newColor);\n        dfs(image, r-1, c, oldColor, newColor);\n        dfs(image, r, c+1, oldColor, newColor);\n        dfs(image, r, c-1, oldColor, newColor);\n    }\n\n    vector<vector<int>> floodFill(vector<vector<int>>& image, int sr, int sc, int newColor) {\n        int oldColor = image[sr][sc];\n        if (oldColor == newColor)\n            return image;\n\n        dfs(image, sr, sc, oldColor, newColor);\n        return image;\n    }\n};\n",
    "user_id": "7f12936a-0622-4715-ad1a-e81e720ca132",
    "action": "run"
  },
  {
    "id": "d41f425a-0196-4dd4-a87b-6f2933570e30",
    "module": "coding",
    "problem_id": "premium-24",
    "problem_title": "Flood Fill",
    "passed_tests": 3,
    "total_tests": 3,
    "percentage": 100.0,
    "timestamp": "2026-02-12T14:28:16.324550",
    "code_submitted": "floodFill <- function(image, sr, sc, newColor) {\n  oldColor <- image[sr+1, sc+1]\n  if (oldColor == newColor) return(image)\n\n  m <- nrow(image)\n  n <- ncol(image)\n\n  dfs <- function(r, c) {\n    if (r < 1 || r > m || c < 1 || c > n)\n      return()\n\n    if (image[r, c] != oldColor)\n      return()\n\n    image[r, c] <<- newColor\n\n    dfs(r+1, c)\n    dfs(r-1, c)\n    dfs(r, c+1)\n    dfs(r, c-1)\n  }\n\n  dfs(sr+1, sc+1)\n  return(image)\n}\n",
    "user_id": "7f12936a-0622-4715-ad1a-e81e720ca132",
    "action": "run"
  },
  {
    "id": "fc21ef8f-b98f-4707-a7cc-09afbad50d2c",
    "module": "coding",
    "problem_id": "premium-24",
    "problem_title": "Flood Fill",
    "passed_tests": 15,
    "total_tests": 15,
    "percentage": 100.0,
    "timestamp": "2026-02-12T14:28:24.513841",
    "code_submitted": "floodFill <- function(image, sr, sc, newColor) {\n  oldColor <- image[sr+1, sc+1]\n  if (oldColor == newColor) return(image)\n\n  m <- nrow(image)\n  n <- ncol(image)\n\n  dfs <- function(r, c) {\n    if (r < 1 || r > m || c < 1 || c > n)\n      return()\n\n    if (image[r, c] != oldColor)\n      return()\n\n    image[r, c] <<- newColor\n\n    dfs(r+1, c)\n    dfs(r-1, c)\n    dfs(r, c+1)\n    dfs(r, c-1)\n  }\n\n  dfs(sr+1, sc+1)\n  return(image)\n}\n",
    "user_id": "7f12936a-0622-4715-ad1a-e81e720ca132",
    "action": "submit"
  }
]