[
  {
    "id": "402e1ca7-f8e4-45a9-907c-9adec4b64b75",
    "module": "coding",
    "problem_id": "premium-46",
    "problem_title": "Word Break II",
    "passed_tests": 3,
    "total_tests": 3,
    "percentage": 100.0,
    "timestamp": "2026-05-04T14:34:24.162848",
    "code_submitted": "def wordBreak(s, wordDict):\n    word_set = set(wordDict)\n    memo = {}\n\n    def dfs(start):\n        # If already computed\n        if start in memo:\n            return memo[start]\n\n        # If reached end \u2192 valid sentence\n        if start == len(s):\n            return [\"\"]\n\n        sentences = []\n\n        for end in range(start + 1, len(s) + 1):\n            word = s[start:end]\n\n            if word in word_set:\n                # Recurse for remaining string\n                sub_sentences = dfs(end)\n\n                for sub in sub_sentences:\n                    # Avoid extra space at end\n                    if sub:\n                        sentences.append(word + \" \" + sub)\n                    else:\n                        sentences.append(word)\n\n        memo[start] = sentences\n        return sentences\n\n    return dfs(0)",
    "user_id": "7f12936a-0622-4715-ad1a-e81e720ca132",
    "action": "run"
  },
  {
    "id": "e99d1080-8f1e-45f2-8056-fae4cdb6fcf8",
    "module": "coding",
    "problem_id": "premium-46",
    "problem_title": "Word Break II",
    "passed_tests": 12,
    "total_tests": 15,
    "percentage": 80.0,
    "timestamp": "2026-05-04T14:34:28.065863",
    "code_submitted": "def wordBreak(s, wordDict):\n    word_set = set(wordDict)\n    memo = {}\n\n    def dfs(start):\n        # If already computed\n        if start in memo:\n            return memo[start]\n\n        # If reached end \u2192 valid sentence\n        if start == len(s):\n            return [\"\"]\n\n        sentences = []\n\n        for end in range(start + 1, len(s) + 1):\n            word = s[start:end]\n\n            if word in word_set:\n                # Recurse for remaining string\n                sub_sentences = dfs(end)\n\n                for sub in sub_sentences:\n                    # Avoid extra space at end\n                    if sub:\n                        sentences.append(word + \" \" + sub)\n                    else:\n                        sentences.append(word)\n\n        memo[start] = sentences\n        return sentences\n\n    return dfs(0)",
    "user_id": "7f12936a-0622-4715-ad1a-e81e720ca132",
    "action": "submit"
  },
  {
    "id": "f4dbc5f8-d37d-4699-9b91-b1c59ef6e7a2",
    "module": "coding",
    "problem_id": "premium-46",
    "problem_title": "Word Break II",
    "passed_tests": 3,
    "total_tests": 3,
    "percentage": 100.0,
    "timestamp": "2026-05-04T14:35:32.017128",
    "code_submitted": "def wordBreak(s, wordDict):\n    word_set = set(wordDict)\n    memo = {}\n\n    # Step 1: DP to check if breakable\n    dp = [False] * (len(s) + 1)\n    dp[0] = True\n\n    for i in range(1, len(s) + 1):\n        for j in range(i):\n            if dp[j] and s[j:i] in word_set:\n                dp[i] = True\n                break\n\n    # Step 2: DFS with pruning\n    def dfs(start):\n        if start in memo:\n            return memo[start]\n\n        if start == len(s):\n            return [\"\"]\n\n        sentences = []\n\n        for end in range(start + 1, len(s) + 1):\n            word = s[start:end]\n\n            # \ud83d\udeab PRUNE: skip if remaining can't form valid sentence\n            if word in word_set and dp[end]:\n                sub_sentences = dfs(end)\n\n                for sub in sub_sentences:\n                    if sub:\n                        sentences.append(word + \" \" + sub)\n                    else:\n                        sentences.append(word)\n\n        memo[start] = sentences\n        return sentences\n\n    return dfs(0)",
    "user_id": "7f12936a-0622-4715-ad1a-e81e720ca132",
    "action": "run"
  },
  {
    "id": "eddf4e62-c634-49c6-b9b8-634cca167c91",
    "module": "coding",
    "problem_id": "premium-46",
    "problem_title": "Word Break II",
    "passed_tests": 12,
    "total_tests": 15,
    "percentage": 80.0,
    "timestamp": "2026-05-04T14:35:35.752500",
    "code_submitted": "def wordBreak(s, wordDict):\n    word_set = set(wordDict)\n    memo = {}\n\n    # Step 1: DP to check if breakable\n    dp = [False] * (len(s) + 1)\n    dp[0] = True\n\n    for i in range(1, len(s) + 1):\n        for j in range(i):\n            if dp[j] and s[j:i] in word_set:\n                dp[i] = True\n                break\n\n    # Step 2: DFS with pruning\n    def dfs(start):\n        if start in memo:\n            return memo[start]\n\n        if start == len(s):\n            return [\"\"]\n\n        sentences = []\n\n        for end in range(start + 1, len(s) + 1):\n            word = s[start:end]\n\n            # \ud83d\udeab PRUNE: skip if remaining can't form valid sentence\n            if word in word_set and dp[end]:\n                sub_sentences = dfs(end)\n\n                for sub in sub_sentences:\n                    if sub:\n                        sentences.append(word + \" \" + sub)\n                    else:\n                        sentences.append(word)\n\n        memo[start] = sentences\n        return sentences\n\n    return dfs(0)",
    "user_id": "7f12936a-0622-4715-ad1a-e81e720ca132",
    "action": "submit"
  },
  {
    "id": "816bb251-f67f-4442-97a9-165d26876e3c",
    "module": "coding",
    "problem_id": "premium-8",
    "problem_title": "Maximum Subarray",
    "passed_tests": 3,
    "total_tests": 3,
    "percentage": 100.0,
    "timestamp": "2026-05-04T14:37:17.112569",
    "code_submitted": "def maxSubArray(nums):\n    current_sum = nums[0]\n    max_sum = nums[0]\n\n    for i in range(1, len(nums)):\n        # Decide whether to extend or restart\n        current_sum = max(nums[i], current_sum + nums[i])\n        \n        # Update global maximum\n        max_sum = max(max_sum, current_sum)\n\n    return max_sum",
    "user_id": "7f12936a-0622-4715-ad1a-e81e720ca132",
    "action": "run"
  },
  {
    "id": "336762bc-c951-4aca-a2b6-82ed5df0ce90",
    "module": "coding",
    "problem_id": "premium-8",
    "problem_title": "Maximum Subarray",
    "passed_tests": 16,
    "total_tests": 16,
    "percentage": 100.0,
    "timestamp": "2026-05-04T14:37:22.175894",
    "code_submitted": "def maxSubArray(nums):\n    current_sum = nums[0]\n    max_sum = nums[0]\n\n    for i in range(1, len(nums)):\n        # Decide whether to extend or restart\n        current_sum = max(nums[i], current_sum + nums[i])\n        \n        # Update global maximum\n        max_sum = max(max_sum, current_sum)\n\n    return max_sum",
    "user_id": "7f12936a-0622-4715-ad1a-e81e720ca132",
    "action": "submit"
  },
  {
    "id": "369c745e-681d-41cd-900d-0488eaa55bd0",
    "module": "coding",
    "problem_id": "premium-8",
    "problem_title": "Maximum Subarray",
    "passed_tests": 0,
    "total_tests": 0,
    "percentage": 0,
    "timestamp": "2026-05-04T14:38:18.478736",
    "code_submitted": "maxSubArray <- function(nums) {\n    current_sum <- nums[1]\n    max_sum <- nums[1]\n    \n    start <- 1\n    end <- 1\n    temp_start <- 1\n    \n    for (i in 2:length(nums)) {\n        if (nums[i] > current_sum + nums[i]) {\n            current_sum <- nums[i]\n            temp_start <- i\n        } else {\n            current_sum <- current_sum + nums[i]\n        }\n        \n        if (current_sum > max_sum) {\n            max_sum <- current_sum\n            start <- temp_start\n            end <- i\n        }\n    }\n    \n    return(nums[start:end])\n}",
    "user_id": "7f12936a-0622-4715-ad1a-e81e720ca132",
    "action": "run"
  },
  {
    "id": "fc7cc4b2-efbf-4a78-b2d8-495d41b9c057",
    "module": "coding",
    "problem_id": "premium-8",
    "problem_title": "Maximum Subarray",
    "passed_tests": 0,
    "total_tests": 0,
    "percentage": 0,
    "timestamp": "2026-05-04T14:38:45.913948",
    "code_submitted": "class Solution {\n    public int maxSubArray(int[] nums) {\n        int currentSum = nums[0];\n        int maxSum = nums[0];\n\n        for (int i = 1; i < nums.length; i++) {\n            currentSum = Math.max(nums[i], currentSum + nums[i]);\n            maxSum = Math.max(maxSum, currentSum);\n        }\n\n        return maxSum;\n    }\n}",
    "user_id": "7f12936a-0622-4715-ad1a-e81e720ca132",
    "action": "run"
  }
]